Metadata-Version: 1.0
Name: HTTPSServer
Version: 0.1
Summary: Simple HTTPS Server
Home-page: https://github.com/yeger00/HTTPSServer
Author: Avi Yeger
Author-email: yeger00@gmail.com
License: MIT
Keywords: https,server
Platform: UNKNOWN
